gpu_utils/__init__.py
gpu_utils/_scripts/__init__.py
gpu_utils/_scripts/gpu.py
gpu_utils/_scripts/kill_interrupted_processes.py
gpu_utils/_scripts/tmux_gpu_info.py
gpu_utils/_version.py
gpu_utils/gpu_printing_config.py
gpu_utils/utils.py
gpu_utils-0.2.8.dist-info/entry_points.txt
gpu_utils-0.2.8.dist-info/LICENSE
gpu_utils-0.2.8.dist-info/WHEEL
gpu_utils-0.2.8.dist-info/METADATA
gpu_utils-0.2.8.dist-info/RECORD
