Metadata-Version: 2.1
Name: gpu-utils
Version: 0.2.8
Summary: Utility functions for working with GPUs.
Home-page: https://github.com/neighthan/gpu-utils
License: MIT
Author: Nathan Hunt
Author-email: neighthan.hunt@gmail.com
Requires-Python: >=3.6,<4.0
Classifier: License :: OSI Approved :: MIT License
Classifier: Programming Language :: Python :: 3
Classifier: Programming Language :: Python :: 3.6
Classifier: Programming Language :: Python :: 3.7
Requires-Dist: colored (>=1.3,<2.0)
Requires-Dist: nvidia-ml-py3 (>=7.352,<8.0)
Requires-Dist: psutil (>=5.6,<6.0)
Project-URL: Repository, https://github.com/neighthan/gpu-utils
